{"web":{"client_id":"408668786741-qdn62q8a534uv98nch8kdhiak4uikbfd.apps.googleusercontent.com","project_id":"studied-reason-384418","auth_uri":"https://accounts.google.com/o/oauth2/auth","token_uri":"https://oauth2.googleapis.com/token","auth_provider_x509_cert_url":"https://www.googleapis.com/oauth2/v1/certs","client_secret":"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","redirect_uris":["http://localhost:8080/oauth2callback","http://youtubereplay-project.wl.r.appspot.com/oauth2callback"],"javascript_origins":["http://localhost:8080","http://youtubereplay-project.wl.r.appspot.com"]}}